verilator_stuff/dual_control_switch/top.v
module top(
	input a,
	input b,
	output f
);
	assign f= a^b;

endmodule

verilator_stuff/dual_control_switch/obj_dir/wave.vcd
$version Generated by VerilatedVcd $end
$timescale 1ps $end

 $scope module TOP $end
  $var wire  1 # a $end
  $var wire  1 $ b $end
  $var wire  1 % f $end
  $scope module top $end
   $var wire  1 # a $end
   $var wire  1 $ b $end
   $var wire  1 % f $end
  $upscope $end
 $upscope $end
$enddefinitions $end


#0
1#
0$
1%
#1
1$
0%
#2
#3
0#
0$
#4
1#
1$
#5
0#
1%
#6
#7
1#
0$
#8
0#
0%
#9
#10
1#
1%
#11
1$
0%
#12
0#
0$
#13
1$
1%
#14
1#
0%
#15
0$
1%
#16
0#
0%
#17
1#
1$
#18
0$
1%
#19
#20
1$
0%
#21
#22
0#
1%
#23
0$
0%
#24
1#
1%
#25
#26
#27
0#
1$
#28
0$
0%
#29
1$
1%
#30
1#
0%
#31
0#
1%
#32
#33
#34
1#
0%
#35
0#
1%
#36
#37
#38
0$
0%
#39
1#
1%
#40
#41
0#
0%
#42
#43
1#
1$
#44
0#
1%
#45
0$
0%
#46
#47
1#
1%
#48
0#
0%
#49
1$
1%
#50
1#
0$
#51
0#
0%
#52
1#
1$
#53
0$
1%
#54
#55
0#
0%
#56
1#
1%
#57
0#
1$
#58
1#
0%
#59
0#
1%
#60
#61
1#
0%
#62
#63
#64
#65
0$
1%
#66
1$
0%
#67
0#
1%
#68
#69
1#
0$
#70
0#
1$
#71
#72
1#
0%
#73
0#
0$
#74
1$
1%
#75
#76
#77
#78
#79
1#
0%
#80
0$
1%
#81
0#
0%
#82
1#
1%
#83
#84
0#
0%
#85
#86
1#
1%
#87
1$
0%
#88
#89
0$
1%
#90
0#
1$
#91
1#
0$
#92
1$
0%
#93
0#
1%
#94
#95
1#
0%
#96
#97
0#
0$
#98
1#
1$
#99
0#
1%
